jiri_gitlab/__init__.py
jiri_gitlab/cli.py
jiri_gitlab-0.2.4.dist-info/METADATA
jiri_gitlab-0.2.4.dist-info/WHEEL
jiri_gitlab-0.2.4.dist-info/entry_points.txt
jiri_gitlab-0.2.4.dist-info/top_level.txt
jiri_gitlab-0.2.4.dist-info/RECORD
